mathverse/__init__.py
mathverse-0.0.0.dev0.dist-info/entry_points.txt
mathverse-0.0.0.dev0.dist-info/LICENSE
mathverse-0.0.0.dev0.dist-info/WHEEL
mathverse-0.0.0.dev0.dist-info/METADATA
mathverse-0.0.0.dev0.dist-info/RECORD
